brian2modelfitting/__init__.py
brian2modelfitting/modelfitting/__init__.py
brian2modelfitting/modelfitting/metric.py
brian2modelfitting/modelfitting/modelfitting.py
brian2modelfitting/modelfitting/optimizer.py
brian2modelfitting/modelfitting/simulation.py
brian2modelfitting/modelfitting/utils.py
brian2modelfitting/tests/__init__.py
brian2modelfitting/tests/test_metric.py
brian2modelfitting/tests/test_modelfitting.py
brian2modelfitting/tests/test_optimizer.py
brian2modelfitting/tests/test_simulation.py
brian2modelfitting/tests/test_utils.py
brian2modelfitting-0.1.dist-info/LICENSE
brian2modelfitting-0.1.dist-info/METADATA
brian2modelfitting-0.1.dist-info/WHEEL
brian2modelfitting-0.1.dist-info/top_level.txt
brian2modelfitting-0.1.dist-info/RECORD
