Metadata-Version: 2.1
Name: brian2modelfitting
Version: 0.1
Summary: Modelfitting Toolbox for the Brian 2 simulator
Home-page: https://github.com/brian-team/brian2modelfitting
Author: Aleksandra Teska, Marcel Stimberg, Romain Brette, Dan Goodman
Author-email: team@briansimulator.org
License: CeCILL-2.1
Keywords: model fitting computational neuroscience
Platform: UNKNOWN
Classifier: Development Status :: 4 - Beta
Classifier: Intended Audience :: Science/Research
Classifier: License :: OSI Approved :: CEA CNRS Inria Logiciel Libre License, version 2.1 (CeCILL-2.1)
Classifier: Natural Language :: English
Classifier: Operating System :: OS Independent
Classifier: Programming Language :: Python
Classifier: Programming Language :: Python :: 3
Classifier: Topic :: Scientific/Engineering :: Bio-Informatics
Provides: brian2modelfitting
Requires-Dist: matplotlib (>=1.3.1)
Requires-Dist: numpy
Requires-Dist: brian2 (>=2.0)
Requires-Dist: setuptools
Requires-Dist: setuptools-scm
Requires-Dist: nevergrad
Requires-Dist: scikit-optimize
Provides-Extra: docs
Requires-Dist: sphinx (>=1.7) ; extra == 'docs'
Provides-Extra: test
Requires-Dist: pytest ; extra == 'test'
